[
    {
    "id": "01",
    "type": "update",
    "date": "2026-01-28",
    "title": "곡 목록 추가 안내",
    "body": "'히나 - 커버곡 - 계절범죄'의 목록 추가 완료했습니다."
  },
    {
    "id": "01",
    "type": "update",
    "date": "2026-01-27",
    "title": "곡 목록 추가 안내",
    "body": "'히나 - 커버곡 - Alice in 冷凍庫(Alice in 냉동고)'의 목록 추가 완료했습니다."
  },
    {
    "id": "01",
    "type": "update",
    "date": "2026-01-25",
    "title": "곡 목록 추가 안내",
    "body": "'리코 - 커버곡 - 夜に駆ける(밤을 달리다)'의 목록 추가 완료했습니다."
  },
    {
    "id": "01",
    "type": "update",
    "date": "2026-01-24",
    "title": "곡 목록 추가 안내",
    "body": "'린 - 커버곡 - カガリビト(카가리비토)'의 목록 추가 완료했습니다."
  },
{
    "id": "01",
    "type": "update",
    "date": "2026-01-19",
    "title": "곡 목록 추가 안내",
    "body": "'나나 - 커버곡 - レイン(레인)'의 목록 추가 완료했습니다."
  },
 {
    "id": "01",
    "type": "bugfix",
    "date": "2026-01-07",
    "title": "버그 수정 완료 안내",
    "body": "리코 - 커버곡 목록 진입 불가 현상 해결 \n리제 - J-POP Mashup! 목록 진입 불가 현상 해결 \n목록이 나오지 않을 경우 캐시 삭제 후 재실행 해주세요."
  },
 {
    "id": "02",
    "type": "update",
    "date": "2026-01-06",
    "title": "곡 번호 추가 안내",
    "body": "しわあわせ(주름맞추기)의 TJ 번호 추가 완료했습니다."
  },
 {
    "id": "01",
    "type": "update",
    "date": "2026-01-06",
    "title": "곡 목록 추가 안내",
    "body": "히나 - 커버곡 - メルト(Melt) 목록 추가 완료했습니다."
  },
 {
    "id": "01",
    "type": "update",
    "date": "2025-12-26",
    "title": "곡 번호 추가 안내",
    "body": "怪獣の花唄(괴수의 꽃노래)의 KY 번호 추가 완료했습니다."
  },
 {
    "id": "04",
    "type": "update",
    "date": "2025-12-25",
    "title": "목록 내용 추가 안내",
    "body": "2025/12/25 업로드된 곡들 목록 추가 완료했습니다."
  },
  {
    "id": "02",
    "type": "update",
    "date": "2025-12-25",
    "title": "목록 내용 추가 안내",
    "body": "린 - 커버곡 - All I Want For Christmas Is You 목록 추가 완료했습니다."
  },
  {
    "id": "01",
    "type": "update",
    "date": "2025-12-25",
    "title": "곡 정보 업데이트 안내",
    "body": "부키 - 커버곡 - sabotage TJ 번호 추가 완료했습니다."
  },
  {
    "id": "03",
    "type": "update",
    "date": "2025-12-21",
    "title": "STAR TRAIL 목록 추가 안내",
    "body": "STAR TRAIL 곡 목록 추가 완료했습니다."
  },
  {
    "id": "01",
    "type": "update",
    "date": "2025-12-22",
    "title": "앱 기능 추가 안내",
    "body": "뒤로가기 버튼을 2회 눌러 앱 종료, 즐겨찾기 목록 정렬 방법 기능을 추가 완료했습니다."
  },
  {
    "id": "01",
    "type": "update",
    "date": "2025-12-18",
    "title": "곡 목록 데이터 추가 안내",
    "body": "리제 - 커버곡 - ケセラセラ(케세라세라) 곡 목록 추가 완료했습니다."
  },
  {
    "id": "01",
    "type": "update",
    "date": "2025-12-13",
    "title": "곡 목록 데이터 추가 안내",
    "body": "멤버 전체, 스텔라이브 채널 업로드 곡 목록 추가를 완료했습니다."
  },
  {
    "id": "01",
    "type": "update",
    "date": "2025-12-11",
    "title": "곡목록 데이터 추가 안내",
    "body": "유니, 히나, 시로, 리제, 타비, 부키, 린의 곡 목록 갱신을 완료했습니다."
  },
  {
    "id": "01",
    "type": "update",
    "date": "2025-01-01",
    "title": "데이터 업데이트 안내",
    "body": "아이리 칸나 콘서트 곡 데이터가 추가되었습니다!"
  },
  {
    "id": "01",
    "type": "bugfix",
    "date": "2025-12-07",
    "title": "버그 수정 안내",
    "body": "TJ 60 시리즈 번호 색 표시 버그를 수정했습니다."
  },
  {
    "id": "01",
    "type": "update",
    "date": "2025-12-08",
    "title": "기능 추가 안내",
    "body": "즐겨찾기, 검색 기능이 추가되었습니다."
  },
  {
    "id": "02",
    "type": "update",
    "date": "2025-12-08",
    "title": "기능 추가 안내",
    "body": "각 멤버들의 오리지널곡 목록 갱신을 완료했습니다."
  }
]
